[{
    "content":"我的李晨啊 怎么这么悲惨",
    "weight":1
},
{
"content":"电影《心花怒放》里面李晨就露了几秒钟的镜头。",
"weight":1
},
    {
        "content":"期待！",
        "weight":1
    },
    {
        "content":"很好看的一部戏，加油!!!",
        "weight":1
    },
    {
        "content":"爱馨予的赞",
        "weight":1
    },
    {
        "content":"武媚娘和李世民洗澡的出来了吗？",
        "weight":1
    },
    {
        "content":"顶浙江卫视，去你的芒果台",
        "weight":1
    },
    {
        "content":"这是赤裸裸的撕胯大战",
        "weight":1
    },
    {
        "content":"跟范冰冰的不一样？",
        "weight":1
    }
]
